{"_id": "d9bbb5cf-f37d-4dce-9aff-9cb3bc56d2a0", "bboxes": [{"id": "488160c7-6d5d-4bb1-9bf9-f112280b4375", "label": null, "x_max": 953, "x_min": 821, "y_max": 2341, "y_min": 2210}, {"id": "314dcca4-26ae-4ea7-af3d-1c0f84490074", "label": null, "x_max": 710, "x_min": 580, "y_max": 2348, "y_min": 2202}, {"id": "8308c214-b71e-4046-9839-6d637447b8da", "label": null, "x_max": 3304, "x_min": 3178, "y_max": 2228, "y_min": 2085}, {"id": "ccb9ce4a-3d2e-4d95-bc56-200251379f9e", "label": null, "x_max": 3311, "x_min": 3175, "y_max": 2093, "y_min": 1958}, {"id": "a76b693c-7bdd-4620-80d3-b6ecf22cfc64", "label": null, "x_max": 3548, "x_min": 3415, "y_max": 1950, "y_min": 1815}, {"id": "de29e8de-bc90-4954-80b0-62edafc59272", "label": "\u6148", "x_max": 480, "x_min": 340, "y_max": 1939, "y_min": 1815}, {"id": "ce54fd31-25be-4cfc-8bd6-2d86e34bfef2", "label": "\u5176", "x_max": 710, "x_min": 577, "y_max": 1958, "y_min": 1811}, {"id": "da2607a4-117a-4edb-aa8c-359086183412", "label": null, "x_max": 2376, "x_min": 2225, "y_max": 1954, "y_min": 1804}, {"id": "dd906ab0-2df8-4a3c-bbcd-f701f0cf1cfa", "label": "\u5e25", "x_max": 3311, "x_min": 3175, "y_max": 1819, "y_min": 1684}, {"id": "8472228e-ec71-4436-b1fe-afca3cef49e2", "label": null, "x_max": 473, "x_min": 355, "y_max": 1804, "y_min": 1680}, {"id": "84cc861f-8029-412e-81ae-f877c2588640", "label": "\u7372", "x_max": 710, "x_min": 580, "y_max": 1819, "y_min": 1665}, {"id": "1a387728-a089-4f71-8105-2b72856e138c", "label": null, "x_max": 3315, "x_min": 3178, "y_max": 1684, "y_min": 1545}, {"id": "db6c5147-886f-47a3-b7c2-8bc1d83587d3", "label": null, "x_max": 2365, "x_min": 2229, "y_max": 1687, "y_min": 1545}, {"id": "c6754aa7-61e8-4230-821a-389b8acdb960", "label": null, "x_max": 487, "x_min": 348, "y_max": 1665, "y_min": 1538}, {"id": "8951252b-52b9-4fca-9c22-c96e59592332", "label": ":", "x_max": 3322, "x_min": 3182, "y_max": 1545, "y_min": 1421}, {"id": "66d4d3e3-014a-4fc0-84ae-013a013638c5", "label": "\u5468", "x_max": 3092, "x_min": 2946, "y_max": 1541, "y_min": 1413}, {"id": "f450b3de-e7ac-4122-ac7d-36ad3e196f97", "label": null, "x_max": 480, "x_min": 348, "y_max": 1534, "y_min": 1391}, {"id": "36fc7dfc-3ed4-4661-99fa-7d14a311101c", "label": "\u95d5", "x_max": 3798, "x_min": 3648, "y_max": 1421, "y_min": 1275}, {"id": "fd0b50f5-f939-48dd-a540-7508db82bf3a", "label": "\u5f9e", "x_max": 3089, "x_min": 2942, "y_max": 1402, "y_min": 1278}, {"id": "efa948c7-da6a-4cb3-a011-301069abad28", "label": null, "x_max": 2608, "x_min": 2459, "y_max": 1427, "y_min": 1272}, {"id": "9115537e-387c-4815-8b67-bd5a7afd50bf", "label": null, "x_max": 3322, "x_min": 3189, "y_max": 1406, "y_min": 1275}, {"id": "cff0b17a-1787-44f6-8102-642ecccf89d4", "label": null, "x_max": 480, "x_min": 355, "y_max": 1402, "y_min": 1275}, {"id": "82eb4842-30ab-4760-bd7a-69062b1faf3c", "label": null, "x_max": 2612, "x_min": 2469, "y_max": 1275, "y_min": 1139}, {"id": "8f062477-a5a9-4eff-9d22-761052d903c7", "label": "5", "x_max": 3089, "x_min": 2938, "y_max": 1282, "y_min": 1132}, {"id": "0211426d-6770-4198-9e0a-a2fd03548b7d", "label": "\u4e8c", "x_max": 3791, "x_min": 3651, "y_max": 1150, "y_min": 1012}, {"id": "cfc971e1-129a-40fe-b2fd-134aaf93ddd8", "label": null, "x_max": 3078, "x_min": 2953, "y_max": 1132, "y_min": 1012}, {"id": "e84e39ee-2ff1-4b5d-957c-8b9777430f50", "label": null, "x_max": 3791, "x_min": 3655, "y_max": 1012, "y_min": 877}, {"id": "54e5d5f9-b462-49fe-affb-25e369de8dc1", "label": "[", "x_max": 1437, "x_min": 1294, "y_max": 997, "y_min": 866}, {"id": "d614be1c-cc08-490f-8ad2-42dfd548e003", "label": null, "x_max": 3089, "x_min": 2953, "y_max": 873, "y_min": 741}, {"id": "706725dd-68f4-4d38-9d27-dfcc593e97f8", "label": null, "x_max": 4020, "x_min": 3884, "y_max": 756, "y_min": 617}, {"id": "e4383b0a-cd79-41ea-a31a-b53f166f0eb2", "label": null, "x_max": 4031, "x_min": 3874, "y_max": 614, "y_min": 471}, {"id": "9ab142e8-2ffd-4d99-9c7a-8e23d9fa7a00", "label": "\u5ca9", "x_max": 3791, "x_min": 3651, "y_max": 606, "y_min": 467}, {"id": "id1650858394926", "label": null, "x_min": 69.875, "x_max": 150.5, "y_min": 510.625, "y_max": 607.375}, {"id": "id1650858399737", "label": null, "x_min": 182.75, "x_max": 268.75, "y_min": 505.25, "y_max": 596.625}, {"id": "id1650858406747", "label": null, "x_min": 80.625, "x_max": 252.625, "y_min": 634.25, "y_max": 763.25}, {"id": "id1650858413526", "label": null, "x_min": 80.625, "x_max": 241.875, "y_min": 768.625, "y_max": 897.625}, {"id": "id1650858418916", "label": null, "x_min": 86, "x_max": 236.5, "y_min": 897.625, "y_max": 1026.625}, {"id": "id1650858424225", "label": null, "x_min": 75.25, "x_max": 258, "y_min": 1026.625, "y_max": 1155.625}, {"id": "id1650858429226", "label": null, "x_min": 86, "x_max": 241.875, "y_min": 1155.625, "y_max": 1290}, {"id": "id1650858434246", "label": null, "x_min": 96.75, "x_max": 247.25, "y_min": 1295.375, "y_max": 1419}, {"id": "id1650858440671", "label": null, "x_min": 91.375, "x_max": 252.625, "y_min": 1424.375, "y_max": 1553.375}, {"id": "id1650858445855", "label": null, "x_min": 91.375, "x_max": 247.25, "y_min": 1548, "y_max": 1687.75}, {"id": "id1650858450395", "label": null, "x_min": 86, "x_max": 247.25, "y_min": 1693.125, "y_max": 1822.125}, {"id": "id1650858455845", "label": null, "x_min": 69.875, "x_max": 258, "y_min": 1827.5, "y_max": 1956.5}, {"id": "id1650858461755", "label": null, "x_min": 86, "x_max": 252.625, "y_min": 1961.875, "y_max": 2096.25}, {"id": "id1650858466995", "label": null, "x_min": 91.375, "x_max": 268.75, "y_min": 2101.625, "y_max": 2230.625}, {"id": "id1650858472115", "label": null, "x_min": 96.75, "x_max": 258, "y_min": 2236, "y_max": 2359.625}, {"id": "id1650858476575", "label": null, "x_min": 107.5, "x_max": 258, "y_min": 2365, "y_max": 2510.125}, {"id": "id1650858481576", "label": null, "x_min": 102.125, "x_max": 258, "y_min": 2515.5, "y_max": 2639.125}, {"id": "id1650858486075", "label": null, "x_min": 107.5, "x_max": 274.125, "y_min": 2644.5, "y_max": 2789.625}, {"id": "id1650858490896", "label": null, "x_min": 338.625, "x_max": 467.625, "y_min": 499.875, "y_max": 628.875}, {"id": "id1650858495496", "label": null, "x_min": 311.75, "x_max": 473, "y_min": 639.625, "y_max": 768.625}, {"id": "id1650858500635", "label": null, "x_min": 317.125, "x_max": 473, "y_min": 774, "y_max": 892.25}, {"id": "id1650858514987", "label": null, "x_min": 322.5, "x_max": 489.125, "y_min": 897.625, "y_max": 1026.625}, {"id": "id1650858519186", "label": null, "x_min": 333.25, "x_max": 473, "y_min": 1032, "y_max": 1150.25}, {"id": "id1650858525785", "label": null, "x_min": 338.625, "x_max": 473, "y_min": 1155.625, "y_max": 1290}, {"id": "id1650858529995", "label": null, "x_min": 344, "x_max": 473, "y_min": 1956.5, "y_max": 2101.625}, {"id": "id1650858535256", "label": null, "x_min": 344, "x_max": 489.125, "y_min": 2107, "y_max": 2230.625}, {"id": "id1650858540887", "label": null, "x_min": 344, "x_max": 489.125, "y_min": 2236, "y_max": 2370.375}, {"id": "id1650858545846", "label": null, "x_min": 338.625, "x_max": 505.25, "y_min": 2375.75, "y_max": 2494}, {"id": "id1650858550576", "label": null, "x_min": 333.25, "x_max": 494.5, "y_min": 2499.375, "y_max": 2644.5}, {"id": "id1650858555016", "label": null, "x_min": 338.625, "x_max": 510.625, "y_min": 2649.875, "y_max": 2795}, {"id": "id1650858559736", "label": null, "x_min": 537.5, "x_max": 720.25, "y_min": 478.375, "y_max": 623.5}, {"id": "id1650858564106", "label": null, "x_min": 559, "x_max": 704.125, "y_min": 639.625, "y_max": 747.125}, {"id": "id1650858569405", "label": null, "x_min": 553.625, "x_max": 704.125, "y_min": 757.875, "y_max": 897.625}, {"id": "id1650858574805", "label": null, "x_min": 559, "x_max": 709.5, "y_min": 903, "y_max": 1026.625}, {"id": "id1650858581146", "label": null, "x_min": 569.75, "x_max": 709.5, "y_min": 1026.625, "y_max": 1155.625}, {"id": "id1650858587169", "label": null, "x_min": 559, "x_max": 720.25, "y_min": 1161, "y_max": 1284.625}, {"id": "id1650858593480", "label": null, "x_min": 575.125, "x_max": 709.5, "y_min": 1295.375, "y_max": 1413.625}, {"id": "id1650858599629", "label": null, "x_min": 559, "x_max": 720.25, "y_min": 1419, "y_max": 1558.75}, {"id": "id1650858605610", "label": null, "x_min": 580.5, "x_max": 714.875, "y_min": 1564.125, "y_max": 1660.875}, {"id": "id1650858610799", "label": null, "x_min": 569.75, "x_max": 725.625, "y_min": 1961.875, "y_max": 2080.125}, {"id": "id1650858616309", "label": null, "x_min": 564.375, "x_max": 731, "y_min": 2085.5, "y_max": 2209.125}, {"id": "id1650858621029", "label": null, "x_min": 580.5, "x_max": 736.375, "y_min": 2348.875, "y_max": 2510.125}, {"id": "id1650858626191", "label": null, "x_min": 559, "x_max": 747.125, "y_min": 2515.5, "y_max": 2639.125}, {"id": "id1650858630800", "label": null, "x_min": 575.125, "x_max": 725.625, "y_min": 2649.875, "y_max": 2795}, {"id": "id1650858635040", "label": null, "x_min": 784.75, "x_max": 967.5, "y_min": 483.75, "y_max": 628.875}, {"id": "id1650858640339", "label": null, "x_min": 795.5, "x_max": 951.375, "y_min": 639.625, "y_max": 752.5}, {"id": "id1650858645739", "label": null, "x_min": 790.125, "x_max": 946, "y_min": 763.25, "y_max": 881.5}, {"id": "id1650858655660", "label": null, "x_min": 800.875, "x_max": 956.75, "y_min": 892.25, "y_max": 1015.875}, {"id": "id1650858660539", "label": null, "x_min": 795.5, "x_max": 946, "y_min": 1021.25, "y_max": 1161}, {"id": "id1650858673780", "label": null, "x_min": 795.5, "x_max": 951.375, "y_min": 1171.75, "y_max": 1284.625}, {"id": "id1650858678391", "label": null, "x_min": 795.5, "x_max": 962.125, "y_min": 1295.375, "y_max": 1413.625}, {"id": "id1650858683609", "label": null, "x_min": 800.875, "x_max": 967.5, "y_min": 1424.375, "y_max": 1553.375}, {"id": "id1650858690080", "label": null, "x_min": 800.875, "x_max": 972.875, "y_min": 1564.125, "y_max": 1693.125}, {"id": "id1650858694959", "label": null, "x_min": 795.5, "x_max": 967.5, "y_min": 1703.875, "y_max": 1827.5}, {"id": "id1650858699569", "label": null, "x_min": 806.25, "x_max": 956.75, "y_min": 1832.875, "y_max": 1951.125}, {"id": "id1650858704029", "label": null, "x_min": 811.625, "x_max": 956.75, "y_min": 1951.125, "y_max": 2090.875}, {"id": "id1650858709349", "label": null, "x_min": 817, "x_max": 962.125, "y_min": 2101.625, "y_max": 2225.25}, {"id": "id1650858714094", "label": null, "x_min": 817, "x_max": 967.5, "y_min": 2343.5, "y_max": 2499.375}, {"id": "id1650858718949", "label": null, "x_min": 817, "x_max": 972.875, "y_min": 2504.75, "y_max": 2639.125}, {"id": "id1650858723007", "label": null, "x_min": 817, "x_max": 967.5, "y_min": 2644.5, "y_max": 2778.875}, {"id": "id1650858726649", "label": null, "x_min": 1032, "x_max": 1198.625, "y_min": 483.75, "y_max": 612.75}, {"id": "id1650858731199", "label": null, "x_min": 1037.375, "x_max": 1171.75, "y_min": 618.125, "y_max": 747.125}, {"id": "id1650858736550", "label": null, "x_min": 1032, "x_max": 1187.875, "y_min": 747.125, "y_max": 886.875}, {"id": "id1650858741349", "label": null, "x_min": 1032, "x_max": 1187.875, "y_min": 897.625, "y_max": 1021.25}, {"id": "id1650858746329", "label": null, "x_min": 1032, "x_max": 1187.875, "y_min": 1026.625, "y_max": 1144.875}, {"id": "id1650858750840", "label": null, "x_min": 1026.625, "x_max": 1187.875, "y_min": 1150.25, "y_max": 1284.625}, {"id": "id1650858763140", "label": null, "x_min": 1042.75, "x_max": 1193.25, "y_min": 1290, "y_max": 1424.375}, {"id": "id1650858767940", "label": null, "x_min": 1042.75, "x_max": 1182.5, "y_min": 1424.375, "y_max": 1558.75}, {"id": "id1650858772470", "label": null, "x_min": 1048.125, "x_max": 1193.25, "y_min": 1564.125, "y_max": 1693.125}, {"id": "id1650858777469", "label": null, "x_min": 1268.5, "x_max": 1419, "y_min": 483.75, "y_max": 623.5}, {"id": "id1650858782760", "label": null, "x_min": 1252.375, "x_max": 1429.75, "y_min": 623.5, "y_max": 747.125}, {"id": "id1650858788370", "label": null, "x_min": 1268.5, "x_max": 1424.375, "y_min": 752.5, "y_max": 870.75}, {"id": "id1650858794660", "label": null, "x_min": 1273.875, "x_max": 1429.75, "y_min": 1005.125, "y_max": 1155.625}, {"id": "id1650858799578", "label": null, "x_min": 1268.5, "x_max": 1419, "y_min": 1155.625, "y_max": 1284.625}, {"id": "id1650858805287", "label": null, "x_min": 1279.25, "x_max": 1429.75, "y_min": 1290, "y_max": 1413.625}, {"id": "id1650858810768", "label": null, "x_min": 1279.25, "x_max": 1429.75, "y_min": 1413.625, "y_max": 1553.375}, {"id": "id1650858815269", "label": null, "x_min": 1273.875, "x_max": 1435.125, "y_min": 1558.75, "y_max": 1682.375}, {"id": "id1650858819838", "label": null, "x_min": 1273.875, "x_max": 1435.125, "y_min": 1693.125, "y_max": 1811.375}, {"id": "id1650858824318", "label": null, "x_min": 1279.25, "x_max": 1435.125, "y_min": 1822.125, "y_max": 1951.125}, {"id": "id1650858828898", "label": null, "x_min": 1295.375, "x_max": 1429.75, "y_min": 1956.5, "y_max": 2080.125}, {"id": "id1650858834179", "label": null, "x_min": 1290, "x_max": 1435.125, "y_min": 2096.25, "y_max": 2219.875}, {"id": "id1650858839299", "label": null, "x_min": 1290, "x_max": 1429.75, "y_min": 2219.875, "y_max": 2338.125}, {"id": "id1650858843428", "label": null, "x_min": 1284.625, "x_max": 1445.875, "y_min": 2338.125, "y_max": 2494}, {"id": "id1650858847564", "label": null, "x_min": 1290, "x_max": 1451.25, "y_min": 2504.75, "y_max": 2633.75}, {"id": "id1650858850779", "label": null, "x_min": 1284.625, "x_max": 1445.875, "y_min": 2639.125, "y_max": 2778.875}, {"id": "id1650858854659", "label": null, "x_min": 1505, "x_max": 1655.5, "y_min": 473, "y_max": 628.875}, {"id": "id1650858859089", "label": null, "x_min": 1478.125, "x_max": 1569.5, "y_min": 645, "y_max": 741.75}, {"id": "id1650858863720", "label": null, "x_min": 1591, "x_max": 1693.125, "y_min": 639.625, "y_max": 741.75}, {"id": "id1650858867880", "label": null, "x_min": 1521.125, "x_max": 1655.5, "y_min": 747.125, "y_max": 881.5}, {"id": "id1650858873258", "label": null, "x_min": 1510.375, "x_max": 1655.5, "y_min": 876.125, "y_max": 1010.5}, {"id": "id1650858877839", "label": null, "x_min": 1494.25, "x_max": 1666.25, "y_min": 1015.875, "y_max": 1171.75}, {"id": "id1650858881849", "label": null, "x_min": 1494.25, "x_max": 1666.25, "y_min": 1187.875, "y_max": 1263.125}, {"id": "id1650858886758", "label": null, "x_min": 1510.375, "x_max": 1666.25, "y_min": 1284.625, "y_max": 1408.25}, {"id": "id1650858892739", "label": null, "x_min": 1499.625, "x_max": 1666.25, "y_min": 1419, "y_max": 1548}, {"id": "id1650858898479", "label": null, "x_min": 1505, "x_max": 1671.625, "y_min": 1553.375, "y_max": 1677}, {"id": "id1650858905682", "label": null, "x_min": 1515.75, "x_max": 1660.875, "y_min": 1682.375, "y_max": 1816.75}, {"id": "id1650858910108", "label": null, "x_min": 1526.5, "x_max": 1650.125, "y_min": 1822.125, "y_max": 1951.125}, {"id": "id1650858914619", "label": null, "x_min": 1515.75, "x_max": 1660.875, "y_min": 1961.875, "y_max": 2080.125}, {"id": "id1650858919070", "label": null, "x_min": 1521.125, "x_max": 1666.25, "y_min": 2085.5, "y_max": 2246.75}, {"id": "id1650858923779", "label": null, "x_min": 1741.5, "x_max": 1881.25, "y_min": 462.25, "y_max": 612.75}, {"id": "id1650858929209", "label": null, "x_min": 1741.5, "x_max": 1902.75, "y_min": 618.125, "y_max": 757.875}, {"id": "id1650858933619", "label": null, "x_min": 1752.25, "x_max": 1875.875, "y_min": 763.25, "y_max": 892.25}, {"id": "id1650858937989", "label": null, "x_min": 1746.875, "x_max": 1892, "y_min": 897.625, "y_max": 1010.5}, {"id": "id1650858942589", "label": null, "x_min": 1741.5, "x_max": 1892, "y_min": 1010.5, "y_max": 1134.125}, {"id": "id1650858947291", "label": null, "x_min": 1752.25, "x_max": 1886.625, "y_min": 1144.875, "y_max": 1284.625}, {"id": "id1650858952679", "label": null, "x_min": 1752.25, "x_max": 1892, "y_min": 1284.625, "y_max": 1413.625}, {"id": "id1650858956780", "label": null, "x_min": 1746.875, "x_max": 1892, "y_min": 1419, "y_max": 1553.375}, {"id": "id1650858961429", "label": null, "x_min": 1757.625, "x_max": 1892, "y_min": 1564.125, "y_max": 1677}, {"id": "id1650858965486", "label": null, "x_min": 1763, "x_max": 1897.375, "y_min": 1687.75, "y_max": 1811.375}, {"id": "id1650858970790", "label": null, "x_min": 1746.875, "x_max": 1897.375, "y_min": 1816.75, "y_max": 1945.75}, {"id": "id1650858988402", "label": null, "x_min": 1741.5, "x_max": 1897.375, "y_min": 1951.125, "y_max": 2085.5}, {"id": "id1650858993289", "label": null, "x_min": 1741.5, "x_max": 1892, "y_min": 2085.5, "y_max": 2209.125}, {"id": "id1650858998539", "label": null, "x_min": 1757.625, "x_max": 1897.375, "y_min": 2219.875, "y_max": 2348.875}, {"id": "id1650859002940", "label": null, "x_min": 1752.25, "x_max": 1913.5, "y_min": 2354.25, "y_max": 2488.625}, {"id": "id1650859007779", "label": null, "x_min": 1741.5, "x_max": 1918.875, "y_min": 2494, "y_max": 2644.5}, {"id": "id1650859013475", "label": null, "x_min": 1746.875, "x_max": 1918.875, "y_min": 2649.875, "y_max": 2778.875}, {"id": "id1650859018036", "label": null, "x_min": 1956.5, "x_max": 2150, "y_min": 64.5, "y_max": 188.125}, {"id": "id1650859023006", "label": null, "x_min": 1972.625, "x_max": 2144.625, "y_min": 188.125, "y_max": 274.125}, {"id": "id1650859029071", "label": null, "x_min": 1956.5, "x_max": 2150, "y_min": 279.5, "y_max": 381.625}, {"id": "id1650859034965", "label": null, "x_min": 1956.5, "x_max": 2150, "y_min": 381.625, "y_max": 456.875}, {"id": "id1650859041205", "label": null, "x_min": 1967.25, "x_max": 2128.5, "y_min": 467.625, "y_max": 548.25}, {"id": "id1650859046626", "label": null, "x_min": 1961.875, "x_max": 2144.625, "y_min": 553.625, "y_max": 655.75}, {"id": "id1650859051368", "label": null, "x_min": 1961.875, "x_max": 2133.875, "y_min": 661.125, "y_max": 752.5}, {"id": "id1650859057666", "label": null, "x_min": 1961.875, "x_max": 2150, "y_min": 757.875, "y_max": 897.625}, {"id": "id1650859063167", "label": null, "x_min": 1935, "x_max": 2160.75, "y_min": 1015.875, "y_max": 1134.125}, {"id": "id1650859068725", "label": null, "x_min": 1972.625, "x_max": 2128.5, "y_min": 1144.875, "y_max": 1241.625}, {"id": "id1650859074007", "label": null, "x_min": 1967.25, "x_max": 2150, "y_min": 1247, "y_max": 1343.75}, {"id": "id1650859077506", "label": null, "x_min": 2064, "x_max": 2171.5, "y_min": 2096.25, "y_max": 2209.125}, {"id": "id1650859081976", "label": null, "x_min": 2203.75, "x_max": 2365, "y_min": 489.125, "y_max": 618.125}, {"id": "id1650859086730", "label": null, "x_min": 2214.5, "x_max": 2354.25, "y_min": 628.875, "y_max": 741.75}, {"id": "id1650859091196", "label": null, "x_min": 2219.875, "x_max": 2365, "y_min": 752.5, "y_max": 892.25}, {"id": "id1650859096766", "label": null, "x_min": 2214.5, "x_max": 2354.25, "y_min": 886.875, "y_max": 1005.125}, {"id": "id1650859101306", "label": null, "x_min": 2203.75, "x_max": 2354.25, "y_min": 1015.875, "y_max": 1139.5}, {"id": "id1650859105666", "label": null, "x_min": 2209.125, "x_max": 2370.375, "y_min": 1150.25, "y_max": 1279.25}, {"id": "id1650859110975", "label": null, "x_min": 2209.125, "x_max": 2370.375, "y_min": 1284.625, "y_max": 1408.25}, {"id": "id1650859118586", "label": null, "x_min": 2193, "x_max": 2375.75, "y_min": 1413.625, "y_max": 1542.625}, {"id": "id1650859123476", "label": null, "x_min": 2225.25, "x_max": 2365, "y_min": 1693.125, "y_max": 1795.25}, {"id": "id1650859129336", "label": null, "x_min": 2219.875, "x_max": 2370.375, "y_min": 1951.125, "y_max": 2069.375}, {"id": "id1650859134296", "label": null, "x_min": 2214.5, "x_max": 2375.75, "y_min": 2069.375, "y_max": 2193}, {"id": "id1650859138577", "label": null, "x_min": 2219.875, "x_max": 2375.75, "y_min": 2203.75, "y_max": 2338.125}, {"id": "id1650859143436", "label": null, "x_min": 2219.875, "x_max": 2381.125, "y_min": 2348.875, "y_max": 2477.875}, {"id": "id1650859147446", "label": null, "x_min": 2236, "x_max": 2391.875, "y_min": 2477.875, "y_max": 2617.625}, {"id": "id1650859151292", "label": null, "x_min": 2246.75, "x_max": 2386.5, "y_min": 2633.75, "y_max": 2746.625}, {"id": "id1650859156456", "label": null, "x_min": 2424.125, "x_max": 2606.875, "y_min": 86, "y_max": 231.125}, {"id": "id1650859161517", "label": null, "x_min": 2445.625, "x_max": 2606.875, "y_min": 241.875, "y_max": 338.625}, {"id": "id1650859166236", "label": null, "x_min": 2451, "x_max": 2590.75, "y_min": 344, "y_max": 467.625}, {"id": "id1650859171117", "label": null, "x_min": 2418.75, "x_max": 2606.875, "y_min": 478.375, "y_max": 628.875}, {"id": "id1650859175429", "label": null, "x_min": 2451, "x_max": 2612.25, "y_min": 634.25, "y_max": 752.5}, {"id": "id1650859180356", "label": null, "x_min": 2418.75, "x_max": 2601.5, "y_min": 763.25, "y_max": 876.125}, {"id": "id1650859184729", "label": null, "x_min": 2451, "x_max": 2590.75, "y_min": 886.875, "y_max": 1015.875}, {"id": "id1650859191126", "label": null, "x_min": 2440.25, "x_max": 2606.875, "y_min": 1015.875, "y_max": 1139.5}, {"id": "id1650859196260", "label": null, "x_min": 2671.375, "x_max": 2821.875, "y_min": 478.375, "y_max": 612.75}, {"id": "id1650859200947", "label": null, "x_min": 2666, "x_max": 2832.625, "y_min": 618.125, "y_max": 752.5}, {"id": "id1650859205269", "label": null, "x_min": 2687.5, "x_max": 2838, "y_min": 757.875, "y_max": 886.875}, {"id": "id1650859213989", "label": null, "x_min": 2682.125, "x_max": 2821.875, "y_min": 892.25, "y_max": 1010.5}, {"id": "id1650859218667", "label": null, "x_min": 2692.875, "x_max": 2827.25, "y_min": 1021.25, "y_max": 1161}, {"id": "id1650859223482", "label": null, "x_min": 2913.25, "x_max": 3074.5, "y_min": 225.75, "y_max": 354.75}, {"id": "id1650859235062", "label": null, "x_min": 2902.5, "x_max": 3085.25, "y_min": 360.125, "y_max": 483.75}, {"id": "id1650859239512", "label": null, "x_min": 2907.875, "x_max": 3085.25, "y_min": 483.75, "y_max": 618.125}, {"id": "id1650859244262", "label": null, "x_min": 2924, "x_max": 3079.875, "y_min": 618.125, "y_max": 752.5}, {"id": "id1650859253846", "label": null, "x_min": 2929.375, "x_max": 3074.5, "y_min": 876.125, "y_max": 1005.125}, {"id": "id1650859259464", "label": null, "x_min": 2918.625, "x_max": 3074.5, "y_min": 1542.625, "y_max": 1698.5}, {"id": "id1650859264042", "label": null, "x_min": 2940.125, "x_max": 3074.5, "y_min": 1703.875, "y_max": 1811.375}, {"id": "id1650859268193", "label": null, "x_min": 2924, "x_max": 3079.875, "y_min": 1811.375, "y_max": 1935}, {"id": "id1650859273182", "label": null, "x_min": 2924, "x_max": 3069.125, "y_min": 1940.375, "y_max": 2080.125}, {"id": "id1650859277112", "label": null, "x_min": 2934.75, "x_max": 3074.5, "y_min": 2080.125, "y_max": 2187.625}, {"id": "id1650859282432", "label": null, "x_min": 2918.625, "x_max": 3079.875, "y_min": 2193, "y_max": 2327.375}, {"id": "id1650859287793", "label": null, "x_min": 2929.375, "x_max": 3090.625, "y_min": 2332.75, "y_max": 2467.125}, {"id": "id1650859292506", "label": null, "x_min": 2929.375, "x_max": 3096, "y_min": 2483.25, "y_max": 2612.25}, {"id": "id1650859296599", "label": null, "x_min": 2945.5, "x_max": 3101.375, "y_min": 2628.375, "y_max": 2778.875}, {"id": "id1650859301905", "label": null, "x_min": 3139, "x_max": 3316.375, "y_min": 80.625, "y_max": 225.75}, {"id": "id1650859307175", "label": null, "x_min": 3160.5, "x_max": 3289.5, "y_min": 231.125, "y_max": 344}, {"id": "id1650859313673", "label": null, "x_min": 3149.75, "x_max": 3305.625, "y_min": 344, "y_max": 478.375}, {"id": "id1650859318665", "label": null, "x_min": 3165.875, "x_max": 3294.875, "y_min": 489.125, "y_max": 612.75}, {"id": "id1650859325284", "label": null, "x_min": 3149.75, "x_max": 3311, "y_min": 618.125, "y_max": 747.125}, {"id": "id1650859329893", "label": null, "x_min": 3155.125, "x_max": 3300.25, "y_min": 747.125, "y_max": 881.5}, {"id": "id1650859335403", "label": null, "x_min": 3144.375, "x_max": 3311, "y_min": 881.5, "y_max": 1021.25}, {"id": "id1650859340374", "label": null, "x_min": 3160.5, "x_max": 3305.625, "y_min": 1026.625, "y_max": 1144.875}, {"id": "id1650859345495", "label": null, "x_min": 3165.875, "x_max": 3311, "y_min": 1144.875, "y_max": 1273.875}, {"id": "id1650859352967", "label": null, "x_min": 3176.625, "x_max": 3311, "y_min": 1827.5, "y_max": 1940.375}, {"id": "id1650859361452", "label": null, "x_min": 3160.5, "x_max": 3316.375, "y_min": 2230.625, "y_max": 2322}, {"id": "id1650859366681", "label": null, "x_min": 3182, "x_max": 3321.75, "y_min": 2332.75, "y_max": 2467.125}, {"id": "id1650859372002", "label": null, "x_min": 3171.25, "x_max": 3327.125, "y_min": 2467.125, "y_max": 2617.625}, {"id": "id1650859376355", "label": null, "x_min": 3176.625, "x_max": 3332.5, "y_min": 2623, "y_max": 2757.375}, {"id": "id1650859381414", "label": null, "x_min": 3386.25, "x_max": 3536.75, "y_min": 483.75, "y_max": 612.75}, {"id": "id1650859386323", "label": null, "x_min": 3391.625, "x_max": 3531.375, "y_min": 618.125, "y_max": 741.75}, {"id": "id1650859391073", "label": null, "x_min": 3375.5, "x_max": 3558.25, "y_min": 747.125, "y_max": 876.125}, {"id": "id1650859395601", "label": null, "x_min": 3375.5, "x_max": 3547.5, "y_min": 881.5, "y_max": 1010.5}, {"id": "id1650859404793", "label": null, "x_min": 3397, "x_max": 3552.875, "y_min": 1021.25, "y_max": 1144.875}, {"id": "id1650859409463", "label": null, "x_min": 3391.625, "x_max": 3542.125, "y_min": 1150.25, "y_max": 1279.25}, {"id": "id1650859413866", "label": null, "x_min": 3386.25, "x_max": 3547.5, "y_min": 1279.25, "y_max": 1408.25}, {"id": "id1650859420025", "label": null, "x_min": 3402.375, "x_max": 3526, "y_min": 1419, "y_max": 1531.875}, {"id": "id1650859425474", "label": null, "x_min": 3386.25, "x_max": 3547.5, "y_min": 1542.625, "y_max": 1671.625}, {"id": "id1650859431256", "label": null, "x_min": 3386.25, "x_max": 3542.125, "y_min": 1677, "y_max": 1806}, {"id": "id1650859436155", "label": null, "x_min": 3612, "x_max": 3773.25, "y_min": 612.75, "y_max": 741.75}, {"id": "id1650859441867", "label": null, "x_min": 3628.125, "x_max": 3784, "y_min": 747.125, "y_max": 876.125}, {"id": "id1650859447197", "label": null, "x_min": 3612, "x_max": 3784, "y_min": 1161, "y_max": 1273.875}, {"id": "id1650859452575", "label": null, "x_min": 3853.875, "x_max": 4020.5, "y_min": 91.375, "y_max": 231.125}, {"id": "id1650859457911", "label": null, "x_min": 3853.875, "x_max": 4020.5, "y_min": 231.125, "y_max": 349.375}, {"id": "id1650859464565", "label": null, "x_min": 3853.875, "x_max": 4015.125, "y_min": 354.75, "y_max": 467.625}], "height": 2832, "image_file": "01454_mk8", "width": 4128}